transient_package/__init__.py
transient_package/transient.py
transient_package/scripts/transient_package.py
transient_package-1.0.1.post3.dist-info/LICENSE
transient_package-1.0.1.post3.dist-info/METADATA
transient_package-1.0.1.post3.dist-info/WHEEL
transient_package-1.0.1.post3.dist-info/entry_points.txt
transient_package-1.0.1.post3.dist-info/top_level.txt
transient_package-1.0.1.post3.dist-info/RECORD
