Metadata-Version: 2.1
Name: transient-package
Version: 1.0.1.post3
Summary: CLI utility for creating transient Python packages.
Author-email: sasha0552 <admin@sasha0552.org>
License: MIT
Project-URL: Homepage, https://github.com/sasha0552/transient-package
Classifier: Development Status :: 5 - Production/Stable
Classifier: Environment :: Console
Classifier: Intended Audience :: System Administrators
Classifier: License :: OSI Approved :: MIT License
Classifier: Programming Language :: Python
Classifier: Programming Language :: Python :: 3 :: Only
Classifier: Programming Language :: Python :: 3.8
Classifier: Programming Language :: Python :: 3.9
Classifier: Programming Language :: Python :: 3.10
Classifier: Programming Language :: Python :: 3.11
Classifier: Programming Language :: Python :: 3.12
Classifier: Topic :: System :: Installation/Setup
Requires-Python: >=3.8
License-File: LICENSE
Requires-Dist: click ==8.1.7
Requires-Dist: packaging ==24.1
Requires-Dist: wheel ==0.44.0
